README.md
setup.py
bin/checkbtrfs
bin/login-notify.py
bin/notifator
bin/teleg_bot.py
notifator/__init__.py
notifator/hodiny.py
notifator/notify.py
notifator/notihat.py
notifator/ntfy.py
notifator/telegram.py
notifator/version.py
notifator.egg-info/PKG-INFO
notifator.egg-info/SOURCES.txt
notifator.egg-info/dependency_links.txt
notifator.egg-info/requires.txt
notifator.egg-info/top_level.txt