Metadata-Version: 2.1
Name: notifator
Version: 0.3.10
Summary: Automatically created environment for python package
Author: jaromrax
Author-email: jaromrax@gmail.com
License: GPL2
